Metadata-Version: 2.1
Name: sphinx-elasticsearch
Version: 1.0.1
Summary: Indexes documentation build via Sphinx into elasticsearch
Home-page: https://github.com/zeitonline/sphinx_elasticsearch
Author: Zeit Online
Author-email: zon-backend@zeit.de
License: BSD
Platform: UNKNOWN
Classifier: Programming Language :: Python :: 3
Provides-Extra: test
